simpil/__init__.py
simpil/_metadata.py
simpil/constants.py
simpil/examples.py
simpil/fonts.py
simpil/simpil_image.py
simpil/unittests/__init__.py
simpil/unittests/check_justify_constants.py
simpil/unittests/check_justify_multiline.py
simpil-1.5.0.dist-info/LICENSE.txt
simpil-1.5.0.dist-info/METADATA
simpil-1.5.0.dist-info/WHEEL
simpil-1.5.0.dist-info/entry_points.txt
simpil-1.5.0.dist-info/top_level.txt
simpil-1.5.0.dist-info/RECORD
