Metadata-Version: 2.1
Name: simpil
Version: 1.5.0
Summary: Simplifies the use of Pillow for some basic tasks
Home-page: https://None/daycoder/simpil.git
Author: Hywel Thomas
Author-email: hywel.thomas@mac.com
License: MIT
Download-URL: https://None/daycoder/simpil.git/get/1.5.0.tar
Keywords: report,html
Platform: UNKNOWN
Classifier: Development Status :: 3 - Alpha
Classifier: Intended Audience :: Developers
Classifier: License :: OSI Approved :: MIT License
Classifier: Programming Language :: Python :: 2
Classifier: Programming Language :: Python :: 2.7
Classifier: Programming Language :: Python :: 3
Classifier: Topic :: Utilities
License-File: LICENSE.txt
Requires-Dist: pip (>=18.1)
Requires-Dist: future (>=0.16.0)
Requires-Dist: requests (>=2.19.1)
Requires-Dist: Pillow (>=5.3.0)
